{"name":"BluffinMuffin.Beta","tagline":"This is a Texas Hold'em client and server implemented in java and C#.","body":"#BluffinMuffin.Beta\r\n###Important notes\r\n * **Protocol is now an independant project ([BluffinMuffin.Protocol](https://github.com/Ericmas001/BluffinMuffin.Protocol)).**\r\n * **Server is now an independant project ([BluffinMuffin.Server](https://github.com/Ericmas001/BluffinMuffin.Server)).**\r\n\r\n----\r\n \r\nThis is a Texas Hold'em client and server implemented in java and C#. The Java version hasn't change since 2010 (Beta3) The C# version is currently under developpement during spare time :)\r\n\r\n * Current Version: [Beta6](https://github.com/Ericmas001/BluffinMuffin.Beta/releases/tag/v0.6-beta-6) (2015-04-27)\r\n\r\n![alt tag](https://googledrive.com/host/0B2wUdLMFaj9JX0pPakRnbWZkeTQ/Beta4.png)\r\n\r\n----\r\n\r\n# [Beta 6](https://github.com/Ericmas001/BluffinMuffin.Beta/releases/tag/v0.6-beta-6): April 2015\r\n\r\n * Compatibility\r\n  * Beta6 Client supports servers that implements at least Protocol v1.0\r\n  * Beta6 Server supports clients that implements at least Protocol v1.0\r\n * Downloads\r\n  * [C# Beta6 Client](https://github.com/Ericmas001/BluffinMuffin.Beta/releases/download/v0.6-beta-6/BluffinMuffin.Client.v0.6.zip)\r\n  * [C# Beta6 Server](https://github.com/Ericmas001/BluffinMuffin.Beta/releases/download/v0.6-beta-6/BluffinMuffin.Server.v0.6.zip)\r\n\r\n----\r\n\r\n# [Beta 5](https://github.com/Ericmas001/bluffin-muffin/releases/tag/v0.5-beta.5): April 2015\r\n\r\n * Compatibility\r\n  * Beta5 Client works only with Beta5 Server\r\n  * Beta5 Server works only with Beta5 Client\r\n * Downloads\r\n  * [C# Beta5 Client](https://github.com/Ericmas001/bluffin-muffin/releases/download/v0.5-beta.5/BluffinMuffin.Client.Beta5.zip)\r\n  * [C# Beta5 Server](https://github.com/Ericmas001/bluffin-muffin/releases/download/v0.5-beta.5/BluffinMuffin.Server.Beta5.zip)\r\n\r\n----\r\n# [Beta 4](https://github.com/Ericmas001/bluffin-muffin/releases/tag/v0.4-beta.4): April 2014\r\n\r\n * Compatibility\r\n  * Beta4 Client works only with Beta4 Server\r\n  * Beta4 Server works only with Beta4 Client\r\n * Downloads\r\n  * [C# Beta4 Client](https://github.com/Ericmas001/bluffin-muffin/releases/download/v0.4-beta.4/BluffinMuffinClient.Beta4.2014-04-07.zip)\r\n  * [C# Beta4 Server](https://github.com/Ericmas001/bluffin-muffin/releases/download/v0.4-beta.4/BluffinMuffinServer.Beta4.2014-04-07.zip)\r\n\r\n----\r\n\r\n# [Beta 3](https://github.com/Ericmas001/bluffin-muffin/releases/tag/v0.3-beta.3): October 2010\r\n\r\n * Compatibility\r\n  * Beta2b Client works only with Beta3 Servers\r\n  * Beta3 Client works only with Beta3 Servers\r\n  * Beta3 Servers works only with Beta2b and Beta3 Clients\r\n * Downloads\r\n  * [Java Beta2b Client](https://github.com/Ericmas001/bluffin-muffin/releases/download/v0.3-beta.3/BluffinMuffin.PokerClient.Java.B02b.zip)\r\n  * [Java Beta3 Server](https://github.com/Ericmas001/bluffin-muffin/releases/download/v0.3-beta.3/BluffinMuffin.PokerServer.Java.B03.jar)\r\n  * [C# Beta3 Client](https://github.com/Ericmas001/bluffin-muffin/releases/download/v0.3-beta.3/BluffinMuffin.PokerClient.Net.B03.zip)\r\n  * [C# Beta3 Server](https://github.com/Ericmas001/bluffin-muffin/releases/download/v0.3-beta.3/BluffinMuffin.PokerServer.Net.B03.zip)\r\n\r\n----\r\n\r\n# [Beta 2](https://github.com/Ericmas001/bluffin-muffin/releases/tag/v0.2-beta.2): April 2010\r\n\r\n * Compatibility\r\n  * Beta2 Clients works only with Beta2 Servers\r\n  * Beta2 Servers works only with Beta2 Clients\r\n * Downloads\r\n  * [Java Beta2 Client](https://github.com/Ericmas001/bluffin-muffin/releases/download/v0.2-beta.2/Bluffin.Muffin.Client.zip)\r\n  * [Java Beta2 Server](https://github.com/Ericmas001/bluffin-muffin/releases/download/v0.2-beta.2/Bluffin.Muffin.Server.jar)\r\n  * [C# Beta2 Client](https://github.com/Ericmas001/bluffin-muffin/releases/download/v0.2-beta.2/Bluffin.Muffin.C.Client.zip)\r\n  * [C# Beta2 Server](https://github.com/Ericmas001/bluffin-muffin/releases/download/v0.2-beta.2/Bluffin.Muffin.C.Server.zip)\r\n","google":"UA-18491855-1","note":"Don't delete this file! It's used internally to help with page regeneration."}